battleship/__init__.py
battleship/__main__.py
battleship/console.py
battleship/game.py
battleship/test/__init__.py
battleship/test/base.py
battleship_py-0.2.2.dist-info/LICENSE
battleship_py-0.2.2.dist-info/METADATA
battleship_py-0.2.2.dist-info/WHEEL
battleship_py-0.2.2.dist-info/top_level.txt
battleship_py-0.2.2.dist-info/RECORD
