Metadata-Version: 2.1
Name: battleship-py
Version: 0.2.2
Summary: Simple Battleship game
Home-page: https://github.com/joamag/battleship
Author: João Magalhães
Author-email: joamag@gmail.com
License: Apache License, Version 2.0
Keywords: game battleship
Platform: UNKNOWN
Classifier: Development Status :: 5 - Production/Stable
Classifier: Topic :: Utilities
Classifier: License :: OSI Approved :: Apache Software License
Classifier: Operating System :: OS Independent
Classifier: Programming Language :: Python
Classifier: Programming Language :: Python :: 3.5
Classifier: Programming Language :: Python :: 3.6
Classifier: Programming Language :: Python :: 3.7
Classifier: Programming Language :: Python :: 3.8
Classifier: Programming Language :: Python :: 3.9
Classifier: Programming Language :: Python :: 3.10
Classifier: Programming Language :: Python :: 3.11
License-File: LICENSE
